README.md
setup.py
Package_Robot/__init__.py
Package_Robot/deplacement.py
TP2_Package_Robot_Jomain.egg-info/PKG-INFO
TP2_Package_Robot_Jomain.egg-info/SOURCES.txt
TP2_Package_Robot_Jomain.egg-info/dependency_links.txt
TP2_Package_Robot_Jomain.egg-info/requires.txt
TP2_Package_Robot_Jomain.egg-info/top_level.txt