Metadata-Version: 1.0
Name: TP2-Package-Robot-Jomain
Version: 2.2
Summary: Génération d'une grille avec des méthodes qui permettent de déplacer un robot sur cette grille ou des obstacles peuvent être généré
Home-page: UNKNOWN
Author: Jomain Benoît
Author-email: UNKNOWN
License: UNKNOWN
Platform: UNKNOWN
